web_time_server/__init__.py
web_time_server/server.py
CYB600_nobins_web_time_server-1.0.2.dist-info/LICENSE
CYB600_nobins_web_time_server-1.0.2.dist-info/METADATA
CYB600_nobins_web_time_server-1.0.2.dist-info/WHEEL
CYB600_nobins_web_time_server-1.0.2.dist-info/entry_points.txt
CYB600_nobins_web_time_server-1.0.2.dist-info/top_level.txt
CYB600_nobins_web_time_server-1.0.2.dist-info/RECORD
