Metadata-Version: 2.1
Name: CYB600-nobins-web-time-server
Version: 1.0.2
Summary: UNKNOWN
Home-page: UNKNOWN
License: UNKNOWN
Platform: UNKNOWN
License-File: LICENSE
Requires-Dist: flask
